pysolotools/__init__.py
pysolotools/constants.py
pysolotools/clients/__init__.py
pysolotools/clients/file_strategy.py
pysolotools/consumers/__init__.py
pysolotools/consumers/solo.py
pysolotools/converters/__init__.py
pysolotools/converters/solo2coco.py
pysolotools/converters/solo2yolo.py
pysolotools/core/__init__.py
pysolotools/core/exceptions.py
pysolotools/core/iterators/__init__.py
pysolotools/core/iterators/frame_iterator.py
pysolotools/core/models/__init__.py
pysolotools/core/models/solo.py
pysolotools/stats/__init__.py
pysolotools/stats/handler.py
pysolotools/stats/analyzers/__init__.py
pysolotools/stats/analyzers/base.py
pysolotools/stats/analyzers/bbox_analyzer.py
pysolotools/stats/analyzers/data_analyzer.py
pysolotools/stats/analyzers/image_analysis_analyzer.py
pysolotools/stats/analyzers/keypoint_analyzer.py
pysolotools/stats/deserializers/__init__.py
pysolotools/stats/deserializers/base.py
pysolotools/stats/deserializers/json_deserializer.py
pysolotools/stats/serializers/__init__.py
pysolotools/stats/serializers/base.py
pysolotools/stats/serializers/json_serializer.py
pysolotools-0.3.17.dist-info/LICENSE
pysolotools-0.3.17.dist-info/METADATA
pysolotools-0.3.17.dist-info/WHEEL
pysolotools-0.3.17.dist-info/entry_points.txt
pysolotools-0.3.17.dist-info/top_level.txt
pysolotools-0.3.17.dist-info/RECORD
